cs/py/doc.py
cs_py_doc-20250426.dist-info/WHEEL
cs_py_doc-20250426.dist-info/METADATA
cs_py_doc-20250426.dist-info/RECORD
